Metadata-Version: 1.0
Name: xml-overrider
Version: 0.1.2
Summary: Simple way to override XML values based on based on xpaths
Home-page: https://github.com/victorpantoja/xml_overrider
Author: Victor Pantoja
Author-email: victor.pantoja@gmail.com
License: Proprietary License
Keywords: accounts
Platform: Linux
